lightning/__about__.py
lightning/__init__.py
lightning/__main__.py
lightning/__setup__.py
lightning/__version__.py
lightning/app/__about__.py
lightning/app/__init__.py
lightning/app/__main__.py
lightning/app/__version__.py
lightning/app/api/__init__.py
lightning/app/api/http_methods.py
lightning/app/api/request_types.py
lightning/app/cli/__init__.py
lightning/app/cli/cmd_apps.py
lightning/app/cli/cmd_clusters.py
lightning/app/cli/cmd_init.py
lightning/app/cli/cmd_install.py
lightning/app/cli/cmd_pl_init.py
lightning/app/cli/cmd_react_ui_init.py
lightning/app/cli/core.py
lightning/app/cli/lightning_cli.py
lightning/app/cli/lightning_cli_create.py
lightning/app/cli/lightning_cli_delete.py
lightning/app/cli/lightning_cli_list.py
lightning/app/cli/commands/__init__.py
lightning/app/cli/commands/app_commands.py
lightning/app/cli/commands/connection.py
lightning/app/components/__init__.py
lightning/app/components/training.py
lightning/app/components/database/__init__.py
lightning/app/components/database/client.py
lightning/app/components/database/server.py
lightning/app/components/database/utilities.py
lightning/app/components/python/__init__.py
lightning/app/components/python/popen.py
lightning/app/components/python/tracer.py
lightning/app/components/serve/__init__.py
lightning/app/components/serve/gradio.py
lightning/app/components/serve/serve.py
lightning/app/components/serve/types/__init__.py
lightning/app/components/serve/types/image.py
lightning/app/components/serve/types/type.py
lightning/app/core/__init__.py
lightning/app/core/api.py
lightning/app/core/app.py
lightning/app/core/constants.py
lightning/app/core/flow.py
lightning/app/core/queues.py
lightning/app/core/work.py
lightning/app/frontend/__init__.py
lightning/app/frontend/frontend.py
lightning/app/frontend/stream_lit.py
lightning/app/frontend/streamlit_base.py
lightning/app/frontend/utils.py
lightning/app/frontend/web.py
lightning/app/frontend/panel/__init__.py
lightning-2022.10.25.dist-info/LICENSE
lightning-2022.10.25.dist-info/METADATA
lightning-2022.10.25.dist-info/WHEEL
lightning-2022.10.25.dist-info/entry_points.txt
lightning-2022.10.25.dist-info/top_level.txt
lightning-2022.10.25.dist-info/RECORD
