Metadata-Version: 2.1
Name: lightning
Version: 2022.10.25
Summary: Use Lightning Apps to build everything from production-ready, multi-cloud ML systems to simple research demos.
Home-page: https://github.com/Lightning-AI/lightning
Download-URL: https://github.com/Lightning-AI/lightning
Author: Lightning AI et al.
Author-email: pytorch@lightning.ai
License: Apache-2.0
Project-URL: Bug Tracker, https://github.com/Lightning-AI/lightning/issues
Project-URL: Documentation, https://lightning.ai/lightning-docs
Project-URL: Source Code, https://github.com/Lightning-AI/lightning
Keywords: deep learning,pytorch,AI
Classifier: Environment :: Console
Classifier: Natural Language :: English
Classifier: Development Status :: 4 - Beta
Classifier: Intended Audience :: Developers
Classifier: Topic :: Scientific/Engineering :: Artificial Intelligence
Classifier: Topic :: Scientific/Engineering :: Information Analysis
Classifier: License :: OSI Approved :: Apache Software License
Classifier: Operating System :: OS Independent
Classifier: Programming Language :: Python :: 3
Classifier: Programming Language :: Python :: 3.7
Classifier: Programming Language :: Python :: 3.8
Classifier: Programming Language :: Python :: 3.9
Requires-Python: >=3.7
License-File: LICENSE
Requires-Dist: lightning-cloud (>=0.5.10)
Requires-Dist: packaging
Requires-Dist: deepdiff (>=5.7.0)
Requires-Dist: starsessions (<2.0,>=1.2.1)
Requires-Dist: fsspec (>=2022.5.0)
Requires-Dist: s3fs (>=2022.5.0)
Requires-Dist: croniter (<1.4.0,>=1.3.0)
Requires-Dist: traitlets (>=5.3.0)
Requires-Dist: arrow (>=1.2.0)
Requires-Dist: lightning-utilities (==0.3.*)
Requires-Dist: beautifulsoup4
Requires-Dist: psutil
Requires-Dist: numpy (>=1.17.2)
Requires-Dist: torch (>=1.9.*)
Requires-Dist: tqdm (>=4.57.0)
Requires-Dist: PyYAML (>=5.4)
Requires-Dist: fsspec[http] (>2021.06.0)
Requires-Dist: tensorboard (>=2.9.1)
Requires-Dist: torchmetrics (>=0.7.0)
Requires-Dist: packaging (>=17.0)
Requires-Dist: typing-extensions (>=4.0.0)
